MANIFEST.in
README.txt
requirements.txt
setup.py
helianthus/__init__.py
helianthus/hello.py
helianthus/awd/__init__.py
helianthus/awd/awdconsole.py
helianthus/awd/xingmeng.py
helianthus/ctf/__init__.py
helianthus/ctf/http_ddos.py
helianthus/ctf/md5_scan.py
helianthus/ctf/port_scanner.py
helianthus/other/__init__.py
helianthus/other/tools.py
helianthus_tools.egg-info/PKG-INFO
helianthus_tools.egg-info/SOURCES.txt
helianthus_tools.egg-info/dependency_links.txt
helianthus_tools.egg-info/requires.txt
helianthus_tools.egg-info/top_level.txt